paperai/__init__.py
paperai/api.py
paperai/export.py
paperai/highlights.py
paperai/index.py
paperai/models.py
paperai/query.py
paperai/shell.py
paperai/vectors.py
paperai/report/__init__.py
paperai/report/__main__.py
paperai/report/annotate.py
paperai/report/column.py
paperai/report/common.py
paperai/report/csvr.py
paperai/report/execute.py
paperai/report/markdown.py
paperai/report/task.py
paperai-2.5.0.dist-info/LICENSE
paperai-2.5.0.dist-info/METADATA
paperai-2.5.0.dist-info/WHEEL
paperai-2.5.0.dist-info/entry_points.txt
paperai-2.5.0.dist-info/top_level.txt
paperai-2.5.0.dist-info/RECORD
