Metadata-Version: 2.1
Name: paperai
Version: 2.5.0
Summary: AI for medical and scientific papers
Home-page: https://github.com/neuml/paperai
Author: NeuML
License: Apache 2.0: http://www.apache.org/licenses/LICENSE-2.0
Project-URL: Documentation, https://github.com/neuml/paperai
Project-URL: Issue Tracker, https://github.com/neuml/paperai/issues
Project-URL: Source Code, https://github.com/neuml/paperai
Keywords: search embedding machine-learning nlp medical scientific papers
Classifier: License :: OSI Approved :: Apache Software License
Classifier: Operating System :: OS Independent
Classifier: Programming Language :: Python :: 3
Classifier: Topic :: Scientific/Engineering :: Artificial Intelligence
Classifier: Topic :: Software Development
Classifier: Topic :: Text Processing :: Indexing
Classifier: Topic :: Utilities
Requires-Python: >=3.10
License-File: LICENSE
Requires-Dist: networkx >=2.4
Requires-Dist: PyYAML >=5.3
Requires-Dist: python-dateutil >=2.8.1
Requires-Dist: regex >=2020.5.14
Requires-Dist: rich >=12.0.1
Requires-Dist: staticvectors[train] >=0.2.0
Requires-Dist: text2digits >=0.1.0
Requires-Dist: txtai[api,similarity] >=8.5.0
Requires-Dist: txtmarker >=1.0.0
Provides-Extra: dev
Requires-Dist: black ; extra == 'dev'
Requires-Dist: coverage ; extra == 'dev'
Requires-Dist: coveralls ; extra == 'dev'
Requires-Dist: httpx ; extra == 'dev'
Requires-Dist: pre-commit ; extra == 'dev'
Requires-Dist: pylint ; extra == 'dev'
